README.md
frasco_users_ldap.py
setup.py
frasco_users_ldap.egg-info/PKG-INFO
frasco_users_ldap.egg-info/SOURCES.txt
frasco_users_ldap.egg-info/dependency_links.txt
frasco_users_ldap.egg-info/not-zip-safe
frasco_users_ldap.egg-info/requires.txt
frasco_users_ldap.egg-info/top_level.txt