Metadata-Version: 1.0
Name: frasco-users-ldap
Version: 0.1.9
Summary: LDAP support for Frasco-Users
Home-page: http://github.com/frascoweb/frasco-users-ldap
Author: Maxime Bouroumeau-Fuseau
Author-email: maxime.bouroumeau@gmail.com
License: MIT
Platform: any
